{"duration": 0.6599409580230713, "input_args": {"imgs": "<nibabel.nifti1.Nifti1Image object at 0x7f896a607080>", "extraction_function": "<nilearn.input_data.nifti_labels_masker._ExtractionFunctor object at 0x7f88e85b2198>", "parameters": "{'background_label': 0, 'detrend': True, 'dtype': None, 'high_pass': 0.009, 'labels_img': <nibabel.nifti1.Nifti1Image object at 0x7f88f1bd0080>, 'low_pass': 0.08, 'mask_img': None, 'smoothing_fwhm': None, 'standardize': True, 'strategy': 'mean', 't_r': 2.700000047683716, 'target_shape': None, 'target_affine': None}", "confounds": "array([[-0.14448021],\n       [-0.08415192],\n       [ 0.07433083],\n       [ 0.17375033],\n       [ 0.11405837],\n       [ 0.0460639 ],\n       [-0.02407335],\n       [-0.137137  ],\n       [-0.18368918],\n       [-0.1527309 ],\n       [-0.0843521 ],\n       [-0.06436785],\n       [ 0.10463954],\n       [ 0.15103208],\n       [ 0.15464793],\n       [ 0.02532388],\n       [ 0.09757806],\n       [-0.08125775],\n       [-0.09902048],\n       [ 0.01351383],\n       [ 0.0752563 ],\n       [ 0.09977227],\n       [ 0.07459203],\n       [ 0.00758685],\n       [ 0.073782  ],\n       [ 0.13145193],\n       [ 0.16997407],\n       [ 0.16056298],\n       [ 0.1643114 ],\n       [ 0.10888408],\n       [-0.130783  ],\n       [-0.17217498],\n       [-0.13556705],\n       [-0.09107038],\n       [-0.0834322 ],\n       [-0.12883957],\n       [-0.12623507],\n       [-0.15139118],\n       [-0.09737895],\n       [-0.01537323],\n       [ 0.02835765],\n       [-0.09792138],\n       [-0.1373698 ],\n       [-0.114991  ],\n       [-0.12856823],\n       [-0.12458129],\n       [-0.11726475],\n       [-0.10871489],\n       [-0.09256109],\n       [-0.03811446],\n       [ 0.07423187],\n       [ 0.06606301],\n       [ 0.08506443],\n       [ 0.08006299],\n       [ 0.07717232],\n       [ 0.06614298],\n       [ 0.06662805],\n       [ 0.10169753],\n       [ 0.10841614],\n       [ 0.11516424],\n       [ 0.13790318],\n       [ 0.12681113],\n       [ 0.17189732],\n       [ 0.14654191],\n       [ 0.10111857],\n       [ 0.135437  ],\n       [ 0.1026442 ],\n       [ 0.08106016],\n       [ 0.07177925],\n       [ 0.0841732 ],\n       [ 0.02130165],\n       [-0.05898935],\n       [-0.11530714],\n       [-0.08571324],\n       [-0.10454504],\n       [-0.09453322],\n       [-0.12468021],\n       [-0.14116538],\n       [-0.11049529],\n       [-0.10681737],\n       [-0.09883974],\n       [-0.0633288 ],\n       [-0.0143341 ],\n       [ 0.06983912],\n       [ 0.1257208 ]], dtype=float32)", "copy": "True", "dtype": "None"}}