{"duration": 0.5480561256408691, "input_args": {"imgs": "<nibabel.nifti1.Nifti1Image object at 0x7f8964acbf60>", "extraction_function": "<nilearn.input_data.nifti_labels_masker._ExtractionFunctor object at 0x7f896c21a320>", "parameters": "{'background_label': 0, 'detrend': True, 'dtype': None, 'high_pass': 0.009, 'labels_img': <nibabel.nifti1.Nifti1Image object at 0x7f88d6fd5208>, 'low_pass': 0.08, 'mask_img': None, 'smoothing_fwhm': None, 'standardize': True, 'strategy': 'mean', 't_r': 2.5, 'target_shape': None, 'target_affine': None}", "confounds": "array([[-0.03717829],\n       [ 0.02407253],\n       [-0.07466034],\n       [ 0.07494379],\n       [ 0.0785355 ],\n       [-0.09115767],\n       [-0.0469567 ],\n       [-0.0405078 ],\n       [-0.05566197],\n       [-0.05838782],\n       [-0.06048546],\n       [-0.04669309],\n       [-0.06518032],\n       [-0.03539345],\n       [-0.05996577],\n       [ 0.08646473],\n       [ 0.19416717],\n       [ 0.04971625],\n       [-0.08610845],\n       [-0.05571644],\n       [-0.14319721],\n       [ 0.07068574],\n       [-0.10075364],\n       [ 0.11857703],\n       [ 0.0261698 ],\n       [ 0.10005845],\n       [ 0.06461487],\n       [ 0.13942897],\n       [ 0.19481066],\n       [ 0.16749349],\n       [ 0.16115533],\n       [ 0.1857892 ],\n       [ 0.05187862],\n       [ 0.15323144],\n       [ 0.04521541],\n       [-0.0527809 ],\n       [ 0.04710665],\n       [-0.11432315],\n       [-0.08099777],\n       [-0.10928746],\n       [-0.10274874],\n       [-0.12654553],\n       [ 0.06323703],\n       [ 0.08793342],\n       [ 0.04354454],\n       [ 0.10527627],\n       [ 0.14840974],\n       [ 0.09551517],\n       [ 0.05512878],\n       [ 0.02927755],\n       [ 0.05188417],\n       [-0.11989717],\n       [-0.12742832],\n       [-0.12115612],\n       [-0.11807529],\n       [-0.14249474],\n       [-0.14636378],\n       [-0.1178057 ],\n       [-0.15169999],\n       [-0.1793464 ],\n       [-0.1436395 ],\n       [-0.10352907],\n       [-0.12401461],\n       [-0.16750352],\n       [-0.1560357 ],\n       [ 0.00364433],\n       [-0.14466745],\n       [-0.06370821],\n       [-0.10220544],\n       [-0.11338946],\n       [ 0.05999446],\n       [ 0.12507275],\n       [ 0.17880632],\n       [ 0.19840501],\n       [ 0.1530581 ],\n       [ 0.12824222],\n       [ 0.1323354 ],\n       [ 0.16677211],\n       [ 0.11448977],\n       [-0.06971852],\n       [-0.02959378],\n       [ 0.11181779]], dtype=float32)", "copy": "True", "dtype": "None"}}