{"duration": 1.661485195159912, "input_args": {"imgs": "<nibabel.nifti1.Nifti1Image object at 0x7f89607872b0>", "extraction_function": "<nilearn.input_data.nifti_labels_masker._ExtractionFunctor object at 0x7f88e858c320>", "parameters": "{'background_label': 0, 'detrend': True, 'dtype': None, 'high_pass': 0.009, 'labels_img': <nibabel.nifti1.Nifti1Image object at 0x7f88f894dac8>, 'low_pass': 0.08, 'mask_img': None, 'smoothing_fwhm': None, 'standardize': True, 'strategy': 'mean', 't_r': 2.0, 'target_shape': None, 'target_affine': None}", "confounds": "array([[-0.01954732],\n       [ 0.02288833],\n       [-0.02940365],\n       [ 0.03430999],\n       [-0.05298394],\n       [ 0.00761242],\n       [ 0.03406509],\n       [-0.06732465],\n       [-0.01311954],\n       [ 0.12441133],\n       [-0.00748289],\n       [ 0.01410726],\n       [ 0.05146062],\n       [-0.12347597],\n       [ 0.10644005],\n       [ 0.01115315],\n       [-0.042868  ],\n       [ 0.07075101],\n       [-0.08294577],\n       [ 0.05573485],\n       [ 0.02970706],\n       [-0.01533904],\n       [ 0.0339011 ],\n       [-0.04970166],\n       [ 0.05530587],\n       [-0.07195466],\n       [ 0.07608113],\n       [-0.10446142],\n       [ 0.04119952],\n       [-0.04483001],\n       [-0.00322043],\n       [ 0.00578571],\n       [-0.06625876],\n       [-0.00696225],\n       [ 0.05716093],\n       [-0.04892901],\n       [-0.09578013],\n       [ 0.00145877],\n       [ 0.07175529],\n       [-0.10285016],\n       [ 0.06600798],\n       [ 0.01993565],\n       [-0.1162525 ],\n       [-0.01480806],\n       [ 0.1289103 ],\n       [ 0.00910947],\n       [-0.13890098],\n       [ 0.05762725],\n       [ 0.01596773],\n       [-0.13024993],\n       [ 0.06837159],\n       [ 0.08360205],\n       [-0.07348274],\n       [-0.05236923],\n       [ 0.11191436],\n       [ 0.06273148],\n       [-0.13927794],\n       [ 0.03926075],\n       [-0.01174312],\n       [-0.08963954],\n       [ 0.09323817],\n       [ 0.11665487],\n       [-0.11710662],\n       [ 0.06400064],\n       [ 0.01967468],\n       [-0.07631925],\n       [ 0.17343818],\n       [-0.08704259],\n       [ 0.00613715],\n       [ 0.07916084],\n       [-0.08944597],\n       [ 0.07571378],\n       [-0.09451144],\n       [-0.00717521],\n       [ 0.05538961],\n       [ 0.00913917],\n       [-0.07931523],\n       [-0.01072667],\n       [ 0.03695767],\n       [ 0.0665337 ],\n       [-0.09910711],\n       [ 0.03858633],\n       [ 0.07565628],\n       [-0.14103669],\n       [ 0.0945583 ],\n       [-0.03955319],\n       [-0.09074455],\n       [ 0.0072824 ],\n       [ 0.17526293],\n       [-0.07578122],\n       [ 0.02930768],\n       [ 0.00025188],\n       [-0.06389037],\n       [-0.08827802],\n       [ 0.15592611],\n       [ 0.03735383],\n       [-0.06891727],\n       [ 0.16148493],\n       [-0.07799613],\n       [-0.09673718],\n       [ 0.09173524],\n       [ 0.13284136],\n       [-0.18574551],\n       [ 0.00105716],\n       [ 0.09775787],\n       [ 0.06448419],\n       [-0.19180214],\n       [ 0.09533275],\n       [ 0.04081477],\n       [-0.03332621],\n       [-0.00863564],\n       [ 0.0224405 ],\n       [-0.05103043],\n       [ 0.05983956],\n       [-0.09094445],\n       [ 0.09314892],\n       [ 0.04554234],\n       [-0.07197134],\n       [-0.01786017],\n       [ 0.02214479],\n       [-0.11133119],\n       [ 0.17389183],\n       [ 0.03823834],\n       [-0.06241598],\n       [-0.09976065],\n       [ 0.15305288],\n       [-0.04852261],\n       [ 0.05277759],\n       [ 0.10629599],\n       [-0.11808005],\n       [-0.08109851],\n       [ 0.09341481],\n       [ 0.03397017],\n       [-0.05501368],\n       [ 0.12192471],\n       [-0.07248813],\n       [-0.04586748],\n       [ 0.09801403],\n       [-0.14485459],\n       [ 0.08420622],\n       [ 0.01414548],\n       [-0.02623094],\n       [ 0.05069982],\n       [-0.07395752],\n       [ 0.09473923],\n       [-0.00341793],\n       [-0.13432424],\n       [ 0.02487728],\n       [-0.04267471],\n       [-0.01529765],\n       [ 0.09554102],\n       [-0.13686606]], dtype=float32)", "copy": "True", "dtype": "None"}}