{"duration": 0.7482004165649414, "input_args": {"imgs": "<nibabel.nifti1.Nifti1Image object at 0x7f88f1bccef0>", "extraction_function": "<nilearn.input_data.nifti_labels_masker._ExtractionFunctor object at 0x7f88e85b2da0>", "parameters": "{'background_label': 0, 'detrend': True, 'dtype': None, 'high_pass': 0.009, 'labels_img': <nibabel.nifti1.Nifti1Image object at 0x7f896a568828>, 'low_pass': 0.08, 'mask_img': None, 'smoothing_fwhm': None, 'standardize': True, 'strategy': 'mean', 't_r': 2.5, 'target_shape': None, 'target_affine': None}", "confounds": "array([[ 0.00278141],\n       [ 0.0062492 ],\n       [ 0.00434271],\n       [-0.01061341],\n       [-0.01734492],\n       [-0.0167935 ],\n       [-0.00937972],\n       [-0.01908315],\n       [-0.0161857 ],\n       [-0.00946755],\n       [-0.00536065],\n       [-0.0139025 ],\n       [-0.00981032],\n       [-0.01178557],\n       [-0.01755808],\n       [-0.01567418],\n       [-0.01889352],\n       [-0.02386601],\n       [-0.02987254],\n       [-0.03661517],\n       [-0.03846103],\n       [-0.0246503 ],\n       [-0.04076792],\n       [-0.04769737],\n       [-0.0523317 ],\n       [-0.05092239],\n       [-0.05519209],\n       [-0.05572895],\n       [-0.06648042],\n       [-0.07009058],\n       [-0.07524087],\n       [-0.08261356],\n       [-0.08183537],\n       [-0.08630208],\n       [-0.08654509],\n       [-0.08373757],\n       [-0.07674856],\n       [-0.07812413],\n       [-0.08087663],\n       [-0.08012225],\n       [-0.08403162],\n       [-0.08185399],\n       [-0.08057202],\n       [-0.08045086],\n       [-0.08112579],\n       [-0.07749043],\n       [-0.0788508 ],\n       [-0.08492432],\n       [-0.08496571],\n       [-0.04230346],\n       [ 0.01075406],\n       [ 0.00438943],\n       [ 0.05806084],\n       [ 0.12652297],\n       [ 0.11096903],\n       [ 0.16767909],\n       [ 0.12893128],\n       [-0.03505406],\n       [ 0.21331555],\n       [ 0.20875016],\n       [ 0.21647249],\n       [ 0.201463  ],\n       [ 0.18039684],\n       [ 0.15736291],\n       [ 0.16874331],\n       [ 0.1484278 ],\n       [ 0.17518897],\n       [ 0.17019229],\n       [ 0.16306989],\n       [ 0.13587034],\n       [ 0.10102149],\n       [ 0.06479159],\n       [ 0.06302382],\n       [ 0.09468426],\n       [ 0.07099839],\n       [ 0.08515929],\n       [ 0.11314821],\n       [ 0.1303524 ],\n       [ 0.14224301],\n       [ 0.13021204],\n       [ 0.11290682],\n       [ 0.10000458],\n       [ 0.08939175],\n       [ 0.09285253],\n       [ 0.07763182],\n       [ 0.03740044],\n       [ 0.03020053],\n       [ 0.00816778],\n       [ 0.00561647],\n       [-0.01003382],\n       [-0.00838408],\n       [-0.00227353],\n       [ 0.01114261],\n       [-0.00282564],\n       [-0.01121248],\n       [-0.00590407],\n       [-0.00592815],\n       [ 0.01171634],\n       [-0.00309351],\n       [-0.004743  ],\n       [-0.03381993],\n       [-0.05470964],\n       [-0.05792328],\n       [-0.07289452],\n       [-0.07087129],\n       [-0.09037831],\n       [-0.08194757],\n       [-0.14764747],\n       [-0.19844778],\n       [-0.17968263],\n       [-0.14141394],\n       [-0.09634876],\n       [-0.09642806],\n       [-0.09234998],\n       [-0.10264743],\n       [-0.09656318],\n       [-0.13904232],\n       [-0.04904987],\n       [-0.01845885],\n       [-0.04927837]], dtype=float32)", "copy": "True", "dtype": "None"}}