{"duration": 0.7837090492248535, "input_args": {"imgs": "<nibabel.nifti1.Nifti1Image object at 0x7f8960fcbd68>", "extraction_function": "<nilearn.input_data.nifti_labels_masker._ExtractionFunctor object at 0x7f88d6fe06d8>", "parameters": "{'background_label': 0, 'detrend': True, 'dtype': None, 'high_pass': 0.009, 'labels_img': <nibabel.nifti1.Nifti1Image object at 0x7f8960169b38>, 'low_pass': 0.08, 'mask_img': None, 'smoothing_fwhm': None, 'standardize': True, 'strategy': 'mean', 't_r': 2.5, 'target_shape': None, 'target_affine': None}", "confounds": "array([[-0.00948178],\n       [-0.05003706],\n       [-0.08304598],\n       [-0.06229861],\n       [-0.12959853],\n       [-0.0774121 ],\n       [-0.13050075],\n       [-0.06836858],\n       [ 0.01050437],\n       [-0.16035828],\n       [-0.0091128 ],\n       [ 0.00880299],\n       [-0.07469411],\n       [-0.12862848],\n       [-0.02037634],\n       [ 0.04924032],\n       [ 0.03522608],\n       [ 0.00596245],\n       [ 0.0407501 ],\n       [ 0.03777548],\n       [ 0.04690782],\n       [-0.02548634],\n       [-0.07536177],\n       [-0.02554567],\n       [ 0.10583486],\n       [ 0.09823531],\n       [ 0.1049106 ],\n       [ 0.11541764],\n       [ 0.1473533 ],\n       [ 0.15054187],\n       [ 0.11550227],\n       [ 0.03354146],\n       [ 0.07630009],\n       [ 0.08892551],\n       [ 0.05002627],\n       [-0.03687997],\n       [-0.02246732],\n       [ 0.14091857],\n       [ 0.05817297],\n       [-0.01118612],\n       [-0.00654694],\n       [ 0.12871476],\n       [ 0.11707289],\n       [ 0.06993033],\n       [-0.06376413],\n       [ 0.05828147],\n       [ 0.11875666],\n       [-0.00061821],\n       [ 0.08127651],\n       [ 0.09670828],\n       [ 0.09716354],\n       [ 0.01050349],\n       [-0.03666781],\n       [ 0.02259453],\n       [ 0.06588709],\n       [ 0.09409588],\n       [ 0.06123326],\n       [ 0.08604286],\n       [ 0.0631472 ],\n       [ 0.04313915],\n       [ 0.04790064],\n       [-0.05191991],\n       [-0.07961585],\n       [ 0.02723986],\n       [ 0.09507629],\n       [ 0.07809783],\n       [ 0.09171389],\n       [ 0.03003839],\n       [-0.06394193],\n       [-0.10708322],\n       [-0.14306028],\n       [-0.10253114],\n       [-0.09657931],\n       [-0.08347104],\n       [-0.0510583 ],\n       [-0.01796641],\n       [-0.10449461],\n       [-0.1208969 ],\n       [-0.13303414],\n       [-0.16170937],\n       [-0.16689801],\n       [-0.02020866],\n       [-0.11531845],\n       [-0.00907418],\n       [-0.11815326],\n       [-0.13560498],\n       [-0.06216126],\n       [ 0.0207915 ],\n       [-0.15876327],\n       [-0.12247417],\n       [-0.09222315],\n       [-0.1006813 ],\n       [-0.16414408],\n       [-0.02507392],\n       [-0.00222754],\n       [-0.1078926 ],\n       [ 0.00119965],\n       [ 0.00581979],\n       [-0.02950719],\n       [-0.08108111],\n       [ 0.01923923],\n       [-0.08016102],\n       [-0.04287916],\n       [-0.07800117],\n       [ 0.01064194],\n       [-0.0473253 ],\n       [-0.10324883],\n       [ 0.08745154],\n       [-0.00332249],\n       [-0.01988024],\n       [ 0.13629937],\n       [ 0.1130496 ],\n       [ 0.01449937],\n       [ 0.12164375],\n       [ 0.16688403],\n       [ 0.23794684],\n       [ 0.28099883],\n       [ 0.11633613],\n       [ 0.02142026],\n       [ 0.05241865]], dtype=float32)", "copy": "True", "dtype": "None"}}