{"duration": 1.1238396167755127, "input_args": {"imgs": "<nibabel.nifti1.Nifti1Image object at 0x7f88d6fd5ba8>", "extraction_function": "<nilearn.input_data.nifti_labels_masker._ExtractionFunctor object at 0x7f88f1bd0080>", "parameters": "{'background_label': 0, 'detrend': True, 'dtype': None, 'high_pass': 0.009, 'labels_img': <nibabel.nifti1.Nifti1Image object at 0x7f88f1bccf28>, 'low_pass': 0.08, 'mask_img': None, 'smoothing_fwhm': None, 'standardize': True, 'strategy': 'mean', 't_r': 2.0, 'target_shape': None, 'target_affine': None}", "confounds": "array([[-0.09300433],\n       [-0.06809205],\n       [-0.03374714],\n       [ 0.05003586],\n       [ 0.05922637],\n       [ 0.04990225],\n       [-0.0799875 ],\n       [-0.08846202],\n       [-0.1277866 ],\n       [-0.13817824],\n       [-0.06502339],\n       [ 0.01196761],\n       [ 0.02397014],\n       [ 0.01255589],\n       [ 0.04679643],\n       [ 0.03702289],\n       [ 0.02086128],\n       [ 0.00675471],\n       [-0.02013591],\n       [-0.05195585],\n       [-0.07167128],\n       [-0.1017998 ],\n       [-0.13898925],\n       [-0.14410609],\n       [-0.09453088],\n       [-0.01675552],\n       [ 0.04865837],\n       [ 0.06064178],\n       [ 0.05563044],\n       [ 0.04376848],\n       [ 0.0420408 ],\n       [-0.0242871 ],\n       [-0.04479882],\n       [ 0.00509251],\n       [ 0.05381993],\n       [ 0.07620983],\n       [ 0.11895029],\n       [ 0.07762547],\n       [ 0.05733649],\n       [ 0.05717731],\n       [ 0.02518449],\n       [-0.0035283 ],\n       [-0.02941447],\n       [-0.04737392],\n       [-0.07168899],\n       [-0.09812225],\n       [-0.14660494],\n       [-0.17406863],\n       [-0.12653376],\n       [-0.13300642],\n       [-0.11232985],\n       [-0.09526458],\n       [-0.05917357],\n       [ 0.01125014],\n       [ 0.08276033],\n       [-0.05018572],\n       [ 0.00342803],\n       [ 0.09119976],\n       [ 0.03728275],\n       [-0.03211662],\n       [ 0.05089203],\n       [ 0.07825809],\n       [-0.06529461],\n       [-0.01547393],\n       [ 0.10658845],\n       [ 0.06350815],\n       [ 0.14713807],\n       [ 0.17282161],\n       [ 0.17860948],\n       [ 0.06233478],\n       [ 0.03236179],\n       [ 0.12955956],\n       [ 0.09441912],\n       [ 0.04646908],\n       [ 0.05276341],\n       [ 0.07257405],\n       [ 0.04680619],\n       [ 0.03827897],\n       [ 0.03160597],\n       [ 0.05626705],\n       [ 0.0486994 ],\n       [ 0.0790906 ],\n       [-0.02116932],\n       [-0.08763343],\n       [-0.00087349],\n       [ 0.08089459],\n       [ 0.03616426],\n       [-0.06760111],\n       [ 0.03486017],\n       [ 0.1332868 ],\n       [ 0.10751544],\n       [ 0.07248972],\n       [-0.03435391],\n       [ 0.03273436],\n       [ 0.11730158],\n       [-0.08460578],\n       [-0.12257268],\n       [ 0.00786599],\n       [ 0.13082424],\n       [ 0.00277589],\n       [ 0.05740309],\n       [ 0.13104832],\n       [ 0.12156504],\n       [-0.00857765],\n       [ 0.04382008],\n       [ 0.11957347],\n       [ 0.10968596],\n       [ 0.09322967],\n       [ 0.07895461],\n       [ 0.07691126],\n       [ 0.05278356],\n       [ 0.00360329],\n       [-0.04381278],\n       [-0.07696337],\n       [-0.10302628],\n       [-0.07599885],\n       [-0.02236694],\n       [ 0.07787617],\n       [ 0.10299505],\n       [ 0.07664075],\n       [ 0.03657585],\n       [-0.02639874],\n       [-0.13117872],\n       [-0.05897965],\n       [ 0.05060082],\n       [ 0.0886677 ],\n       [ 0.00670227],\n       [-0.10080981],\n       [-0.0725024 ],\n       [ 0.07092697],\n       [-0.00106134],\n       [-0.03844347],\n       [-0.12186444],\n       [-0.09712386],\n       [ 0.03061214],\n       [ 0.02518323],\n       [-0.04112042],\n       [-0.11404794],\n       [-0.16614869],\n       [-0.11591274],\n       [ 0.02309889],\n       [ 0.02108574],\n       [-0.03649169],\n       [-0.09747522],\n       [-0.14254567],\n       [-0.17342013],\n       [-0.142907  ],\n       [-0.10540606],\n       [ 0.0265936 ],\n       [ 0.05783965]], dtype=float32)", "copy": "True", "dtype": "None"}}