{"duration": 0.5597167015075684, "input_args": {"imgs": "<nibabel.nifti1.Nifti1Image object at 0x7f88e85de160>", "extraction_function": "<nilearn.input_data.nifti_labels_masker._ExtractionFunctor object at 0x7f88e88a68d0>", "parameters": "{'background_label': 0, 'detrend': True, 'dtype': None, 'high_pass': 0.009, 'labels_img': <nibabel.nifti1.Nifti1Image object at 0x7f896c2ea978>, 'low_pass': 0.08, 'mask_img': None, 'smoothing_fwhm': None, 'standardize': True, 'strategy': 'mean', 't_r': 2.5, 'target_shape': None, 'target_affine': None}", "confounds": "array([[-0.10287078],\n       [-0.0923301 ],\n       [-0.0912775 ],\n       [-0.13180943],\n       [-0.13689499],\n       [-0.09440072],\n       [-0.06513686],\n       [-0.10266972],\n       [-0.09523795],\n       [-0.11483011],\n       [-0.05683164],\n       [ 0.14693475],\n       [ 0.1168036 ],\n       [ 0.05458915],\n       [ 0.05684398],\n       [-0.02309711],\n       [-0.02459387],\n       [-0.0829964 ],\n       [-0.09930868],\n       [-0.10832986],\n       [-0.08259123],\n       [-0.09316303],\n       [-0.12090488],\n       [-0.09244563],\n       [-0.11555297],\n       [-0.0899938 ],\n       [ 0.13790672],\n       [ 0.09886897],\n       [ 0.08852594],\n       [ 0.13954741],\n       [ 0.12977159],\n       [ 0.05054054],\n       [-0.02050299],\n       [-0.00527786],\n       [ 0.05295836],\n       [ 0.09697939],\n       [ 0.14250006],\n       [ 0.15928468],\n       [ 0.17126898],\n       [ 0.14740793],\n       [ 0.16671285],\n       [ 0.14526641],\n       [ 0.1867325 ],\n       [ 0.18909809],\n       [ 0.17464884],\n       [ 0.11454092],\n       [ 0.12970752],\n       [ 0.14445587],\n       [ 0.00590126],\n       [-0.01995386],\n       [-0.02412693],\n       [-0.09212697],\n       [-0.01593676],\n       [-0.08582135],\n       [ 0.06395862],\n       [ 0.06622867],\n       [ 0.01615223],\n       [ 0.09386408],\n       [ 0.02873715],\n       [-0.01652099],\n       [-0.05817899],\n       [-0.03248888],\n       [ 0.08134724],\n       [ 0.16789955],\n       [ 0.18529958],\n       [ 0.10787604],\n       [-0.01912882],\n       [-0.08101754],\n       [-0.14376217],\n       [-0.12563327],\n       [ 0.14433436],\n       [ 0.07829182],\n       [-0.10582158],\n       [-0.10627428],\n       [-0.1320902 ],\n       [-0.1179817 ],\n       [-0.15167382],\n       [-0.11943059],\n       [-0.15915939],\n       [-0.15521193],\n       [-0.14974535],\n       [-0.12665132]], dtype=float32)", "copy": "True", "dtype": "None"}}