{"duration": 0.5664873123168945, "input_args": {"imgs": "<nibabel.nifti1.Nifti1Image object at 0x7f88d6fe06d8>", "extraction_function": "<nilearn.input_data.nifti_labels_masker._ExtractionFunctor object at 0x7f88d6fe0d30>", "parameters": "{'background_label': 0, 'detrend': True, 'dtype': None, 'high_pass': 0.009, 'labels_img': <nibabel.nifti1.Nifti1Image object at 0x7f88f8958f28>, 'low_pass': 0.08, 'mask_img': None, 'smoothing_fwhm': None, 'standardize': True, 'strategy': 'mean', 't_r': 2.700000047683716, 'target_shape': None, 'target_affine': None}", "confounds": "array([[-0.04277407],\n       [-0.04793483],\n       [-0.04443922],\n       [-0.04568486],\n       [-0.05423662],\n       [-0.05429383],\n       [-0.0526892 ],\n       [-0.04965946],\n       [-0.05547958],\n       [-0.06034682],\n       [-0.05774492],\n       [-0.05734924],\n       [ 0.1241006 ],\n       [-0.0411028 ],\n       [-0.0551106 ],\n       [-0.0559548 ],\n       [-0.05537161],\n       [-0.05902717],\n       [-0.06401511],\n       [-0.06281745],\n       [-0.06700005],\n       [-0.06791576],\n       [-0.06466027],\n       [-0.06739064],\n       [-0.06771789],\n       [-0.06717738],\n       [-0.06610247],\n       [-0.06733057],\n       [-0.06806881],\n       [-0.06942745],\n       [-0.07618321],\n       [-0.07628392],\n       [-0.07076588],\n       [-0.07424004],\n       [-0.07565323],\n       [ 0.0315613 ],\n       [ 0.16443153],\n       [ 0.16917825],\n       [ 0.17363143],\n       [ 0.17673703],\n       [ 0.16632678],\n       [ 0.17482495],\n       [ 0.16967964],\n       [ 0.15126495],\n       [ 0.15740265],\n       [ 0.16820325],\n       [ 0.16632232],\n       [ 0.1627877 ],\n       [ 0.17140126],\n       [ 0.1697283 ],\n       [ 0.17035653],\n       [ 0.16557942],\n       [ 0.1554496 ],\n       [ 0.16686422],\n       [ 0.16217431],\n       [ 0.16255517],\n       [ 0.16461873],\n       [ 0.16465978],\n       [ 0.16432407],\n       [ 0.16219006],\n       [ 0.05108916],\n       [-0.05978652],\n       [-0.06035051],\n       [-0.07485151],\n       [-0.07982754],\n       [-0.07967123],\n       [-0.08053388],\n       [-0.08500189],\n       [-0.0840938 ],\n       [-0.08647474],\n       [-0.08783159],\n       [-0.08810699],\n       [-0.08474609],\n       [-0.08916358],\n       [-0.08970603],\n       [-0.09288017],\n       [-0.09319012],\n       [-0.09647474],\n       [-0.09797256],\n       [-0.10137016],\n       [-0.1014902 ],\n       [-0.10210659],\n       [-0.10346401],\n       [-0.10330722],\n       [-0.10309173]], dtype=float32)", "copy": "True", "dtype": "None"}}