{"duration": 0.9116532802581787, "input_args": {"imgs": "<nibabel.nifti1.Nifti1Image object at 0x7f896c21a358>", "extraction_function": "<nilearn.input_data.nifti_labels_masker._ExtractionFunctor object at 0x7f8964acbf60>", "parameters": "{'background_label': 0, 'detrend': True, 'dtype': None, 'high_pass': 0.009, 'labels_img': <nibabel.nifti1.Nifti1Image object at 0x7f896c2ea978>, 'low_pass': 0.08, 'mask_img': None, 'smoothing_fwhm': None, 'standardize': True, 'strategy': 'mean', 't_r': 3.0, 'target_shape': None, 'target_affine': None}", "confounds": "array([[-0.04920212],\n       [ 0.05903018],\n       [ 0.12373919],\n       [ 0.02436473],\n       [-0.09046964],\n       [-0.13283427],\n       [-0.07042912],\n       [ 0.05648315],\n       [ 0.12965989],\n       [-0.02905304],\n       [-0.1515474 ],\n       [ 0.0022789 ],\n       [ 0.12652221],\n       [-0.09891491],\n       [ 0.07800296],\n       [ 0.02414306],\n       [-0.09631805],\n       [ 0.12019479],\n       [ 0.03225828],\n       [-0.10103021],\n       [-0.13926037],\n       [-0.03079211],\n       [ 0.03661592],\n       [-0.08174488],\n       [ 0.05367219],\n       [ 0.04445087],\n       [-0.14742866],\n       [ 0.0779648 ],\n       [-0.08446132],\n       [-0.03017456],\n       [ 0.05845563],\n       [ 0.01374028],\n       [-0.08177724],\n       [-0.11304247],\n       [ 0.09959846],\n       [ 0.10441083],\n       [ 0.02892478],\n       [-0.14809088],\n       [ 0.00924587],\n       [ 0.16763954],\n       [-0.06186669],\n       [-0.04172769],\n       [ 0.15324168],\n       [-0.07176028],\n       [-0.00202123],\n       [ 0.13595167],\n       [-0.07364126],\n       [-0.09799071],\n       [ 0.05484736],\n       [-0.10222504],\n       [ 0.13257074],\n       [-0.05956349],\n       [ 0.0654204 ],\n       [ 0.09498753],\n       [-0.05995205],\n       [-0.11599118],\n       [-0.02230955],\n       [ 0.09051614],\n       [ 0.10959994],\n       [ 0.11118756],\n       [ 0.09409565],\n       [-0.00409786],\n       [ 0.12000168],\n       [ 0.15301113],\n       [-0.10082418],\n       [-0.04027523],\n       [ 0.15074874],\n       [-0.08452116],\n       [-0.12812401],\n       [ 0.01446872],\n       [ 0.1165514 ],\n       [-0.00330856],\n       [-0.08745841],\n       [-0.08647221],\n       [ 0.08644786],\n       [ 0.16071202],\n       [-0.05937422],\n       [-0.1519452 ],\n       [-0.08483785],\n       [-0.1205964 ],\n       [ 0.09249149],\n       [ 0.16318476],\n       [ 0.03276461],\n       [-0.1141938 ],\n       [ 0.04723535],\n       [ 0.09331112],\n       [-0.11153935],\n       [ 0.0561458 ],\n       [ 0.07023273],\n       [-0.14081253],\n       [ 0.10377428],\n       [ 0.02868735],\n       [-0.10787239],\n       [ 0.11664869],\n       [-0.02980758],\n       [-0.11379601],\n       [ 0.09769838],\n       [-0.06757765],\n       [-0.03744113],\n       [ 0.04866047],\n       [-0.08376458],\n       [-0.0319664 ],\n       [-0.00681137],\n       [ 0.07548844],\n       [-0.1205122 ],\n       [ 0.07405432],\n       [-0.09552732],\n       [-0.00207379],\n       [ 0.04644048],\n       [-0.12734866],\n       [ 0.07840617],\n       [-0.0520638 ],\n       [-0.00201236],\n       [ 0.06820208],\n       [-0.11577941],\n       [ 0.09414622],\n       [-0.0948027 ],\n       [ 0.12166977],\n       [-0.03394097],\n       [ 0.00209968]], dtype=float32)", "copy": "True", "dtype": "None"}}