{"duration": 1.6420607566833496, "input_args": {"imgs": "<nibabel.nifti1.Nifti1Image object at 0x7f88f1bccf28>", "extraction_function": "<nilearn.input_data.nifti_labels_masker._ExtractionFunctor object at 0x7f88e858c6d8>", "parameters": "{'background_label': 0, 'detrend': True, 'dtype': None, 'high_pass': 0.009, 'labels_img': <nibabel.nifti1.Nifti1Image object at 0x7f88e88e7b00>, 'low_pass': 0.08, 'mask_img': None, 'smoothing_fwhm': None, 'standardize': True, 'strategy': 'mean', 't_r': 2.0, 'target_shape': None, 'target_affine': None}", "confounds": "array([[-0.09066477],\n       [-0.08722657],\n       [-0.09497549],\n       [-0.07616637],\n       [-0.07231309],\n       [-0.07080218],\n       [-0.09178669],\n       [-0.10334594],\n       [-0.06057053],\n       [-0.07606372],\n       [-0.08549053],\n       [-0.066207  ],\n       [-0.06310334],\n       [-0.07753912],\n       [-0.06504527],\n       [-0.05643766],\n       [-0.06325952],\n       [-0.05914044],\n       [-0.03704907],\n       [-0.02649893],\n       [-0.03136492],\n       [-0.04710722],\n       [-0.0486601 ],\n       [-0.02590461],\n       [-0.02119462],\n       [-0.03833165],\n       [-0.04187038],\n       [-0.05109585],\n       [-0.0603286 ],\n       [-0.04859804],\n       [-0.06348807],\n       [-0.11342762],\n       [-0.09246613],\n       [-0.06885717],\n       [-0.07403232],\n       [-0.06889375],\n       [-0.04412081],\n       [-0.03473184],\n       [ 0.01005018],\n       [-0.00699783],\n       [ 0.01054832],\n       [ 0.01421199],\n       [ 0.02064809],\n       [ 0.00879096],\n       [ 0.0408534 ],\n       [ 0.05032945],\n       [ 0.0380617 ],\n       [ 0.03159243],\n       [ 0.01934878],\n       [ 0.0460906 ],\n       [ 0.06356172],\n       [ 0.02325623],\n       [ 0.02809845],\n       [ 0.01911875],\n       [ 0.01666788],\n       [ 0.01867217],\n       [ 0.02390538],\n       [ 0.02790702],\n       [ 0.03758618],\n       [ 0.02928275],\n       [ 0.04125383],\n       [ 0.06457588],\n       [ 0.05287779],\n       [ 0.04182292],\n       [ 0.02329344],\n       [ 0.06379653],\n       [ 0.06693695],\n       [ 0.04829298],\n       [ 0.06971093],\n       [ 0.07297762],\n       [ 0.07898705],\n       [ 0.07230759],\n       [ 0.08621383],\n       [ 0.08060102],\n       [ 0.09376781],\n       [ 0.0779964 ],\n       [ 0.09141758],\n       [ 0.1100192 ],\n       [ 0.090964  ],\n       [ 0.11098418],\n       [ 0.11748502],\n       [ 0.11248278],\n       [ 0.09104188],\n       [ 0.11361026],\n       [ 0.11057501],\n       [ 0.10223265],\n       [ 0.10578745],\n       [ 0.11337392],\n       [ 0.10868141],\n       [ 0.10707603],\n       [ 0.08620573],\n       [ 0.08401353],\n       [ 0.07034738],\n       [ 0.08669832],\n       [ 0.09621532],\n       [ 0.08091822],\n       [ 0.06640837],\n       [ 0.06608029],\n       [ 0.06511146],\n       [ 0.0619325 ],\n       [ 0.06106935],\n       [ 0.0656202 ],\n       [ 0.09446599],\n       [ 0.10251737],\n       [ 0.1037575 ],\n       [ 0.10592896],\n       [ 0.10383017],\n       [ 0.0921597 ],\n       [ 0.09126621],\n       [ 0.0848628 ],\n       [ 0.0888349 ],\n       [ 0.06224365],\n       [ 0.06266604],\n       [ 0.10444771],\n       [ 0.10382342],\n       [ 0.08306994],\n       [ 0.07089411],\n       [ 0.083082  ],\n       [ 0.07195744],\n       [ 0.00727551],\n       [-0.01468495],\n       [-0.0161943 ],\n       [-0.04372979],\n       [-0.02529456],\n       [-0.06886262],\n       [-0.08419231],\n       [-0.02378006],\n       [-0.05254078],\n       [-0.07423119],\n       [-0.09580883],\n       [-0.0577576 ],\n       [-0.08879244],\n       [-0.06602655],\n       [-0.03064917],\n       [-0.07389805],\n       [-0.08911996],\n       [-0.11290094],\n       [-0.12963423],\n       [-0.09021698],\n       [-0.11386387],\n       [-0.11892907],\n       [-0.1647073 ],\n       [-0.15427956],\n       [-0.14460851],\n       [-0.15457495],\n       [-0.16278005],\n       [-0.15330532],\n       [-0.15274195],\n       [-0.15729645],\n       [-0.15599597],\n       [-0.1374503 ],\n       [-0.09342448]], dtype=float32)", "copy": "True", "dtype": "None"}}