{"duration": 1.2163548469543457, "input_args": {"imgs": "<nibabel.nifti1.Nifti1Image object at 0x7f88f1bccf98>", "extraction_function": "<nilearn.input_data.nifti_labels_masker._ExtractionFunctor object at 0x7f88e88a6898>", "parameters": "{'background_label': 0, 'detrend': True, 'dtype': None, 'high_pass': 0.009, 'labels_img': <nibabel.nifti1.Nifti1Image object at 0x7f88f1bd0080>, 'low_pass': 0.08, 'mask_img': None, 'smoothing_fwhm': None, 'standardize': True, 'strategy': 'mean', 't_r': 2.0, 'target_shape': None, 'target_affine': None}", "confounds": "array([[-0.0533376 ],\n       [-0.05604815],\n       [-0.0566338 ],\n       [-0.05523968],\n       [-0.05425465],\n       [-0.0581338 ],\n       [-0.05555891],\n       [-0.05572211],\n       [-0.04503408],\n       [-0.05988818],\n       [-0.05692985],\n       [-0.0574659 ],\n       [-0.05869703],\n       [-0.0643275 ],\n       [-0.06478371],\n       [-0.06569524],\n       [-0.06859595],\n       [-0.06881845],\n       [-0.0703778 ],\n       [-0.07067066],\n       [-0.0724738 ],\n       [-0.07043279],\n       [-0.06571084],\n       [-0.0690849 ],\n       [-0.04232899],\n       [-0.04939383],\n       [-0.03709145],\n       [-0.04734215],\n       [-0.03627713],\n       [-0.03609956],\n       [-0.04182012],\n       [-0.03520375],\n       [-0.03236272],\n       [-0.04170711],\n       [-0.03149252],\n       [-0.04326463],\n       [-0.04604825],\n       [-0.03562257],\n       [-0.03949683],\n       [-0.03366936],\n       [-0.0293911 ],\n       [-0.03618417],\n       [-0.05447224],\n       [-0.05149109],\n       [-0.05486461],\n       [-0.05042807],\n       [-0.05170712],\n       [-0.04594481],\n       [-0.04284154],\n       [-0.03900843],\n       [-0.04443363],\n       [-0.05036989],\n       [-0.05157408],\n       [-0.09465421],\n       [ 0.00689556],\n       [ 0.03485494],\n       [ 0.05340706],\n       [ 0.05836066],\n       [ 0.04748511],\n       [ 0.05676752],\n       [ 0.0543407 ],\n       [ 0.05760853],\n       [ 0.07077578],\n       [ 0.10313965],\n       [ 0.12296153],\n       [ 0.1254942 ],\n       [ 0.12188375],\n       [ 0.11346981],\n       [ 0.12084864],\n       [ 0.12424732],\n       [ 0.12685946],\n       [ 0.12508051],\n       [ 0.12172879],\n       [ 0.1206904 ],\n       [ 0.11937641],\n       [ 0.11701496],\n       [ 0.11058384],\n       [ 0.1111256 ],\n       [ 0.11034764],\n       [ 0.10548411],\n       [ 0.10557103],\n       [ 0.10805656],\n       [ 0.09886274],\n       [ 0.09987921],\n       [ 0.10109469],\n       [ 0.09540092],\n       [ 0.09270065],\n       [ 0.09198585],\n       [ 0.09150238],\n       [ 0.09187858],\n       [ 0.08803399],\n       [ 0.08254632],\n       [ 0.08227071],\n       [ 0.08775239],\n       [ 0.0827346 ],\n       [ 0.07748448],\n       [ 0.0842012 ],\n       [ 0.07946083],\n       [ 0.07812183],\n       [ 0.07328339],\n       [ 0.07151572],\n       [ 0.06623188],\n       [ 0.0668865 ],\n       [ 0.06877251],\n       [ 0.06740544],\n       [ 0.06525508],\n       [ 0.05744926],\n       [ 0.05632139],\n       [ 0.05454991],\n       [ 0.04958403],\n       [ 0.04679371],\n       [ 0.04958533],\n       [-0.01267754],\n       [ 0.00438395],\n       [ 0.06235782],\n       [ 0.07129659],\n       [-0.01510725],\n       [-0.1294542 ],\n       [-0.19120345],\n       [-0.0761757 ],\n       [-0.01197685],\n       [-0.00058616],\n       [ 0.03313453],\n       [ 0.01420281],\n       [ 0.01192262],\n       [ 0.02153362],\n       [ 0.01956793],\n       [ 0.0144968 ],\n       [ 0.01827929],\n       [ 0.01803589],\n       [ 0.02516867],\n       [ 0.02221016],\n       [ 0.02013656],\n       [ 0.02285956],\n       [ 0.02032719],\n       [ 0.02221752],\n       [ 0.02341138],\n       [ 0.02194858],\n       [ 0.03547937],\n       [ 0.04146326],\n       [ 0.03609591],\n       [ 0.03917791],\n       [-0.0677034 ],\n       [-0.208814  ],\n       [-0.1788458 ],\n       [-0.00418506],\n       [-0.01782391],\n       [ 0.01637707],\n       [-0.03067998],\n       [-0.21770425],\n       [-0.2305255 ],\n       [-0.22211964],\n       [-0.08045328],\n       [-0.08462075],\n       [-0.08614781],\n       [-0.0840235 ],\n       [-0.06484181],\n       [-0.06500297],\n       [-0.06055237],\n       [-0.05446616],\n       [-0.04887556],\n       [-0.04982831],\n       [-0.0639989 ],\n       [-0.05571299],\n       [-0.04576354],\n       [-0.04284578],\n       [-0.02114071],\n       [-0.01824048],\n       [-0.0176008 ],\n       [-0.01803386],\n       [-0.01575782],\n       [-0.01841035],\n       [-0.01967067],\n       [-0.01976904],\n       [-0.01858743],\n       [-0.02419851],\n       [-0.02389161],\n       [-0.02671036],\n       [-0.0254522 ],\n       [-0.01940885]], dtype=float32)", "copy": "True", "dtype": "None"}}